loader/Sample.py
loader/__init__.py
loader/__main__.py
loader/load.py
fake_samples_loader-1.0.13.dist-info/METADATA
fake_samples_loader-1.0.13.dist-info/WHEEL
fake_samples_loader-1.0.13.dist-info/entry_points.txt
fake_samples_loader-1.0.13.dist-info/top_level.txt
fake_samples_loader-1.0.13.dist-info/RECORD
