Metadata-Version: 2.1
Name: fake-samples-loader
Version: 1.0.13
Summary: Fake Samples Loader
Author-email: Fake Samples Loader <fakesamplesloader@gmail.com>
Keywords: samples,loader
Classifier: License :: OSI Approved :: MIT License
Classifier: Programming Language :: Python
Classifier: Programming Language :: Python :: 3
Requires-Python: >=3.11
